dsync/__init__.py
dsync/data_layout.py
dsync/endpoint.py
dsync/http.py
dsync_sdk-0.1.2.dist-info/DESCRIPTION.rst
dsync_sdk-0.1.2.dist-info/METADATA
dsync_sdk-0.1.2.dist-info/RECORD
dsync_sdk-0.1.2.dist-info/WHEEL
dsync_sdk-0.1.2.dist-info/metadata.json
dsync_sdk-0.1.2.dist-info/top_level.txt
