Metadata-Version: 2.0
Name: dsync-sdk
Version: 0.1.2
Summary: Python SDK for realtime synchronization with DSYNC
Home-page: https://github.com/dsync-dev/python-sdk
Author: DSYNC
Author-email: support@dsync.com
License: Copyright (C) 2017 DSYNC
Requires-Dist: requests
